ytool/__init__.py
ytool/ytool.py
ytool/test/__init__.py
ytool/test/test_yaml_path.py
ytool-0.4.3.data/scripts/ytool
ytool-0.4.3.dist-info/LICENSE
ytool-0.4.3.dist-info/METADATA
ytool-0.4.3.dist-info/WHEEL
ytool-0.4.3.dist-info/top_level.txt
ytool-0.4.3.dist-info/RECORD
